nmrpy/__init__.py
nmrpy/data_objects.py
nmrpy/plotting.py
nmrpy/version.py
nmrpy/docs/NMRPy.pdf
nmrpy/docs/quickstart_tutorial.ipynb
nmrpy/tests/__init__.py
nmrpy/tests/nmrpy_tests.py
nmrpy/tests/test_data/test1.nmrpy
nmrpy/tests/test_data/bruker1/1/acqu
nmrpy/tests/test_data/bruker1/1/acqus
nmrpy/tests/test_data/bruker1/1/fid
nmrpy/tests/test_data/bruker1/1/format.temp
nmrpy/tests/test_data/bruker1/1/pulseprogram
nmrpy/tests/test_data/bruker1/1/scon
nmrpy/tests/test_data/bruker1/1/pdata/1/auditp.txt
nmrpy/tests/test_data/bruker1/1/pdata/1/intrng
nmrpy/tests/test_data/bruker1/1/pdata/1/meta
nmrpy/tests/test_data/bruker1/1/pdata/1/meta.ext
nmrpy/tests/test_data/bruker1/1/pdata/1/outd
nmrpy/tests/test_data/bruker1/1/pdata/1/peaks
nmrpy/tests/test_data/bruker1/1/pdata/1/proc
nmrpy/tests/test_data/bruker1/1/pdata/1/procs
nmrpy/tests/test_data/bruker2/1/WS_FTP.LOG
nmrpy/tests/test_data/bruker2/1/acqu
nmrpy/tests/test_data/bruker2/1/acqum
nmrpy/tests/test_data/bruker2/1/acqums
nmrpy/tests/test_data/bruker2/1/acqus
nmrpy/tests/test_data/bruker2/1/cpdprg2
nmrpy/tests/test_data/bruker2/1/fid
nmrpy/tests/test_data/bruker2/1/format.temp
nmrpy/tests/test_data/bruker2/1/pulseprogram
nmrpy/tests/test_data/bruker2/1/scon
nmrpy/tests/test_data/bruker2/1/pdata/1/1i
nmrpy/tests/test_data/bruker2/1/pdata/1/1r
nmrpy/tests/test_data/bruker2/1/pdata/1/WS_FTP.LOG
nmrpy/tests/test_data/bruker2/1/pdata/1/meta
nmrpy/tests/test_data/bruker2/1/pdata/1/meta.ext
nmrpy/tests/test_data/bruker2/1/pdata/1/outd
nmrpy/tests/test_data/bruker2/1/pdata/1/proc
nmrpy/tests/test_data/bruker2/1/pdata/1/procs
nmrpy/tests/test_data/bruker2/10/WS_FTP.LOG
nmrpy/tests/test_data/bruker2/10/acqu
nmrpy/tests/test_data/bruker2/10/acqum
nmrpy/tests/test_data/bruker2/10/acqums
nmrpy/tests/test_data/bruker2/10/acqus
nmrpy/tests/test_data/bruker2/10/cpdprg2
nmrpy/tests/test_data/bruker2/10/fid
nmrpy/tests/test_data/bruker2/10/format.temp
nmrpy/tests/test_data/bruker2/10/pulseprogram
nmrpy/tests/test_data/bruker2/10/scon
nmrpy-0.2.8.dist-info/LICENSE.txt
nmrpy-0.2.8.dist-info/METADATA
nmrpy-0.2.8.dist-info/WHEEL
nmrpy-0.2.8.dist-info/top_level.txt
nmrpy-0.2.8.dist-info/RECORD
