Metadata-Version: 2.1
Name: nmrpy
Version: 0.2.8
Summary: A suite of tools for processing and analysing NMR spectra in Python.
Home-page: https://github.com/NMRPy/nmrpy
Author: Johann Eicher <johanneicher@gmail.com>, Johann Rohwer <j.m.rohwer@gmail.com>
Author-email: johanneicher@gmail.com, j.m.rohwer@gmail.com
Maintainer: Johann Rohwer
Maintainer-email: j.m.rohwer@gmail.com
License: New BSD
Platform: Windows
Platform: Linux
Platform: macOS
License-File: LICENSE.txt
Requires-Dist: numpy
Requires-Dist: scipy
Requires-Dist: matplotlib (>=3.0.0)
Requires-Dist: ipympl (>=0.4.0)
Requires-Dist: notebook (>=6.0.0)
Requires-Dist: ipython (>=7.0.0)
Requires-Dist: lmfit (>=0.9.10)
Requires-Dist: nmrglue (>=0.6)
